term-ai
term_ai
