Metadata-Version: 2.1
Name: terminalai
Version: 0.0.2
Summary: AI Terminal assistant
Home-page: https://github.com/imnotdev25/Term-ai
Author: Talaviya Bhavik
Author-email: talaviyabhavik@proton.me
License: GNU General Public License v2.0
Project-URL: Bug Report, https://github.com/imnotdev25/Term-ai/issues/new
Classifier: License :: OSI Approved :: GNU General Public License v2 (GPLv2)
Classifier: Intended Audience :: Developers
Classifier: Topic :: Software Development :: Libraries :: Python Modules
Classifier: Programming Language :: Python :: 3.9
Classifier: Programming Language :: Python :: 3.10
Classifier: Programming Language :: Python :: 3.11
License-File: LICENSE
Requires-Dist: google-generativeai
Requires-Dist: rich
Requires-Dist: httpx
